python2latex/__init__.py
python2latex/color.py
python2latex/colormap.py
python2latex/document.py
python2latex/floating_environment.py
python2latex/plot.py
python2latex/table.py
python2latex/template.py
python2latex/tex_base.py
python2latex/tex_environment.py
python2latex/utils.py
python2latex-0.4.1.data/data/version.py
python2latex-0.4.1.dist-info/LICENSE
python2latex-0.4.1.dist-info/METADATA
python2latex-0.4.1.dist-info/WHEEL
python2latex-0.4.1.dist-info/top_level.txt
python2latex-0.4.1.dist-info/RECORD
