Metadata-Version: 2.1
Name: python2latex
Version: 0.4.1
Summary: A Python to LaTeX converter
Home-page: https://github.com/jsleb333/python2latex
Author: Jean-Samuel Leboeuf
Author-email: jean-samuel.leboeuf.1@ulaval.ca
License: UNKNOWN
Platform: UNKNOWN
Classifier: Programming Language :: Python :: 3
Classifier: License :: OSI Approved :: MIT License
Classifier: Operating System :: OS Independent
Requires-Python: >=3.6
License-File: LICENSE
Requires-Dist: numpy
